Users/bnmetrics/.fetchmerc
fetchme/__init__.py
fetchme/__version__.py
fetchme/_cli.py
fetchme/utils.py
fetchme-1.1.1.dist-info/METADATA
fetchme-1.1.1.dist-info/RECORD
fetchme-1.1.1.dist-info/WHEEL
fetchme-1.1.1.dist-info/entry_points.txt
fetchme-1.1.1.dist-info/top_level.txt
