Metadata-Version: 2.1
Name: fetchme
Version: 1.1.1
Summary: package for caching and aliasing long commands
Home-page: https://github.com/BNMetrics/fetchme
Author: Luna Chen
Author-email: luna@bnmetrics.com
License: Apache 2.0
Keywords: alias,cli,command-aliasing,bash-aliasing
Platform: UNKNOWN
Requires-Python: >=3
Requires-Dist: click
Requires-Dist: bnmutils
